ssa_tools/__init__.py
ssa_tools/accelerated.py
ssa_tools/classic.py
ssa_tools/core.py
ssa_tools-1.0.0.dist-info/licenses/LICENSE
ssa_tools-1.0.0.dist-info/METADATA
ssa_tools-1.0.0.dist-info/WHEEL
ssa_tools-1.0.0.dist-info/top_level.txt
ssa_tools-1.0.0.dist-info/RECORD
