Metadata-Version: 2.4
Name: ssa-tools
Version: 1.0.0
Summary: A comprehensive Python package for Singular Spectrum Analysis with accelerated implementation
Home-page: https://github.com/TinoDerb/ssa-tools
Author: Mehieddine Derbas
Author-email: mehyeddin.derbass@gmail.com
Project-URL: Bug Tracker, https://https://github.com/TinoDerb/ssa_tools/issues
Keywords: singular spectrum analysis,signal processing,time series,decomposition,trend extraction,noise reduction
Classifier: Programming Language :: Python :: 3
Classifier: Programming Language :: Python :: 3.7
Classifier: Programming Language :: Python :: 3.8
Classifier: Programming Language :: Python :: 3.9
Classifier: Programming Language :: Python :: 3.10
Classifier: License :: OSI Approved :: MIT License
Classifier: Operating System :: OS Independent
Classifier: Topic :: Scientific/Engineering
Classifier: Topic :: Scientific/Engineering :: Information Analysis
Classifier: Topic :: Scientific/Engineering :: Mathematics
Classifier: Topic :: Scientific/Engineering :: Visualization
Requires-Python: >=3.7
License-File: LICENSE
Requires-Dist: numpy>=1.19.0
Requires-Dist: matplotlib>=3.3.0
Requires-Dist: joblib>=1.0.0
Requires-Dist: numba>=0.53.0
Dynamic: author
Dynamic: author-email
Dynamic: classifier
Dynamic: description
Dynamic: description-content-type
Dynamic: home-page
Dynamic: keywords
Dynamic: license-file
Dynamic: project-url
Dynamic: requires-dist
Dynamic: requires-python
Dynamic: summary
